mf_python_tools/__init__.py
mf_python_tools/tool.py
mf_python_tools/log/__init__.py
mf_python_tools/log/jsonLog.py
mf_python_tools/log/log.py
mf_python_tools/log/loggers.py
mf_python_tools/log/logging_config.py
mf_python_tools/log/mfAdapter.py
mf_python_tools-0.2.dist-info/LICENSE
mf_python_tools-0.2.dist-info/METADATA
mf_python_tools-0.2.dist-info/WHEEL
mf_python_tools-0.2.dist-info/top_level.txt
mf_python_tools-0.2.dist-info/RECORD
