Metadata-Version: 2.1
Name: mf-python-tools
Version: 0.2
Summary: MF some tools for Python
Home-page: https://github.com/fangsy/mf-python-tools
Author: fangsy
Author-email: fsy7901@163.com
License: MIT
Keywords: json,logging
Platform: UNKNOWN
Classifier: Intended Audience :: Developers
Classifier: License :: OSI Approved :: MIT License
Classifier: Programming Language :: Python :: 2.7
Classifier: Programming Language :: Python :: 3
Classifier: Programming Language :: Python :: 3.4
Classifier: Programming Language :: Python :: 3.5
Classifier: Programming Language :: Python :: 3.6
Classifier: Programming Language :: Python :: 3.7
Classifier: Programming Language :: Python :: 3.8
License-File: LICENSE
Requires-Dist: json-logging-py
